duetwebapi/__init__.py
duetwebapi/dwa_factory.py
duetwebapi/api/__init__.py
duetwebapi/api/base.py
duetwebapi/api/dsf_api.py
duetwebapi/api/dwc_api.py
duetwebapi/api/wrapper.py
duetwebapi-1.2.2.dist-info/LICENSE
duetwebapi-1.2.2.dist-info/METADATA
duetwebapi-1.2.2.dist-info/WHEEL
duetwebapi-1.2.2.dist-info/top_level.txt
duetwebapi-1.2.2.dist-info/RECORD
