Metadata-Version: 2.1
Name: duetwebapi
Version: 1.2.2
Summary: Python interface to Duet REST API
Home-page: https://github.com/AndyEveritt/DuetWebAPI
Author: Andy Everitt
Author-email: andreweveritt@e3d-online.com
License: UNKNOWN
Platform: UNKNOWN
Classifier: License :: OSI Approved :: MIT License
Classifier: Programming Language :: Python :: 3
Classifier: Operating System :: OS Independent
Requires-Dist: requests (>=2.22.0)
